{
  "collaborative": false,
  "description": "",
  "external_urls": {
    "spotify": "https://open.spotify.com/playlist/7xOerbbn2JM5gYAXSKUIqh"
  },
  "followers": { "href": null, "total": 0 },
  "href": "https://api.spotify.com/v1/playlists/7xOerbbn2JM5gYAXSKUIqh?locale=*",
  "id": "7xOerbbn2JM5gYAXSKUIqh",
  "images": [
    {
      "height": null,
      "url": "https://i.scdn.co/image/ab67616d00001e026b3fa88bdd4af566fbbf2bbf",
      "width": null
    }
  ],
  "name": "arctic monkeys",
  "owner": {
    "display_name": "wutsqo",
    "external_urls": {
      "spotify": "https://open.spotify.com/user/urwatilwutsqo"
    },
    "href": "https://api.spotify.com/v1/users/urwatilwutsqo",
    "id": "urwatilwutsqo",
    "type": "user",
    "uri": "spotify:user:urwatilwutsqo"
  },
  "primary_color": null,
  "public": true,
  "snapshot_id": "Niw5OTc5NzYwOWM4MWFmNjljNDI1ZDBmMGMwMzZlOGU3ZjJhN2U0NTNk",
  "type": "playlist",
  "uri": "spotify:playlist:7xOerbbn2JM5gYAXSKUIqh",
  "tracks": [
    {
      "added_at": "2022-12-21T03:49:37Z",
      "added_by": {
        "external_urls": {
          "spotify": "https://open.spotify.com/user/urwatilwutsqo"
        },
        "href": "https://api.spotify.com/v1/users/urwatilwutsqo",
        "id": "urwatilwutsqo",
        "type": "user",
        "uri": "spotify:user:urwatilwutsqo"
      },
      "is_local": false,
      "primary_color": null,
      "track": {
        "preview_url": "https://p.scdn.co/mp3-preview/97679b16db33ac5727488e3e7eb5b9c7240c165e?cid=1a2f7e0ab25046f9bc15e34bc6f6c396",
        "available_markets": [
          "AR",
          "AU",
          "AT",
          "BE",
          "BO",
          "BR",
          "BG",
          "CA",
          "CL",
          "CO",
          "CR",
          "CY",
          "CZ",
          "DK",
          "DO",
          "DE",
          "EC",
          "EE",
          "SV",
          "FI",
          "FR",
          "GR",
          "GT",
          "HN",
          "HK",
          "HU",
          "IS",
          "IE",
          "IT",
          "LV",
          "LT",
          "LU",
          "MY",
          "MT",
          "MX",
          "NL",
          "NZ",
          "NI",
          "NO",
          "PA",
          "PY",
          "PE",
          "PH",
          "PL",
          "PT",
          "SG",
          "SK",
          "ES",
          "SE",
          "CH",
          "TW",
          "TR",
          "UY",
          "US",
          "GB",
          "AD",
          "LI",
          "MC",
          "ID",
          "JP",
          "TH",
          "VN",
          "RO",
          "IL",
          "ZA",
          "SA",
          "AE",
          "BH",
          "QA",
          "OM",
          "KW",
          "EG",
          "MA",
          "DZ",
          "TN",
          "LB",
          "JO",
          "PS",
          "IN",
          "KZ",
          "MD",
          "UA",
          "AL",
          "BA",
          "HR",
          "ME",
          "MK",
          "RS",
          "SI",
          "KR",
          "BD",
          "PK",
          "LK",
          "GH",
          "KE",
          "NG",
          "TZ",
          "UG",
          "AG",
          "AM",
          "BS",
          "BB",
          "BZ",
          "BT",
          "BW",
          "BF",
          "CV",
          "CW",
          "DM",
          "FJ",
          "GM",
          "GE",
          "GD",
          "GW",
          "GY",
          "HT",
          "JM",
          "KI",
          "LS",
          "LR",
          "MW",
          "MV",
          "ML",
          "MH",
          "FM",
          "NA",
          "NR",
          "NE",
          "PW",
          "PG",
          "WS",
          "SM",
          "ST",
          "SN",
          "SC",
          "SL",
          "SB",
          "KN",
          "LC",
          "VC",
          "SR",
          "TL",
          "TO",
          "TT",
          "TV",
          "VU",
          "AZ",
          "BN",
          "BI",
          "KH",
          "CM",
          "TD",
          "KM",
          "GQ",
          "SZ",
          "GA",
          "GN",
          "KG",
          "LA",
          "MO",
          "MR",
          "MN",
          "NP",
          "RW",
          "TG",
          "UZ",
          "ZW",
          "BJ",
          "MG",
          "MU",
          "MZ",
          "AO",
          "CI",
          "DJ",
          "ZM",
          "CD",
          "CG",
          "IQ",
          "LY",
          "TJ",
          "VE",
          "ET",
          "XK"
        ],
        "explicit": true,
        "type": "track",
        "episode": false,
        "track": true,
        "album": {
          "available_markets": [
            "AR",
            "AU",
            "AT",
            "BE",
            "BO",
            "BR",
            "BG",
            "CA",
            "CL",
            "CO",
            "CR",
            "CY",
            "CZ",
            "DK",
            "DO",
            "DE",
            "EC",
            "EE",
            "SV",
            "FI",
            "FR",
            "GR",
            "GT",
            "HN",
            "HK",
            "HU",
            "IS",
            "IE",
            "IT",
            "LV",
            "LT",
            "LU",
            "MY",
            "MT",
            "MX",
            "NL",
            "NZ",
            "NI",
            "NO",
            "PA",
            "PY",
            "PE",
            "PH",
            "PL",
            "PT",
            "SG",
            "SK",
            "ES",
            "SE",
            "CH",
            "TW",
            "TR",
            "UY",
            "US",
            "GB",
            "AD",
            "LI",
            "MC",
            "ID",
            "JP",
            "TH",
            "VN",
            "RO",
            "IL",
            "ZA",
            "SA",
            "AE",
            "BH",
            "QA",
            "OM",
            "KW",
            "EG",
            "MA",
            "DZ",
            "TN",
            "LB",
            "JO",
            "PS",
            "IN",
            "KZ",
            "MD",
            "UA",
            "AL",
            "BA",
            "HR",
            "ME",
            "MK",
            "RS",
            "SI",
            "KR",
            "BD",
            "PK",
            "LK",
            "GH",
            "KE",
            "NG",
            "TZ",
            "UG",
            "AG",
            "AM",
            "BS",
            "BB",
            "BZ",
            "BT",
            "BW",
            "BF",
            "CV",
            "CW",
            "DM",
            "FJ",
            "GM",
            "GE",
            "GD",
            "GW",
            "GY",
            "HT",
            "JM",
            "KI",
            "LS",
            "LR",
            "MW",
            "MV",
            "ML",
            "MH",
            "FM",
            "NA",
            "NR",
            "NE",
            "PW",
            "PG",
            "PR",
            "WS",
            "SM",
            "ST",
            "SN",
            "SC",
            "SL",
            "SB",
            "KN",
            "LC",
            "VC",
            "SR",
            "TL",
            "TO",
            "TT",
            "TV",
            "VU",
            "AZ",
            "BN",
            "BI",
            "KH",
            "CM",
            "TD",
            "KM",
            "GQ",
            "SZ",
            "GA",
            "GN",
            "KG",
            "LA",
            "MO",
            "MR",
            "MN",
            "NP",
            "RW",
            "TG",
            "UZ",
            "ZW",
            "BJ",
            "MG",
            "MU",
            "MZ",
            "AO",
            "CI",
            "DJ",
            "ZM",
            "CD",
            "CG",
            "IQ",
            "LY",
            "TJ",
            "VE",
            "ET",
            "XK"
          ],
          "type": "album",
          "album_type": "album",
          "href": "https://api.spotify.com/v1/albums/50Zz8CkIhATKUlQMbHO3k1",
          "id": "50Zz8CkIhATKUlQMbHO3k1",
          "images": [
            {
              "height": 640,
              "url": "https://i.scdn.co/image/ab67616d0000b2736b3fa88bdd4af566fbbf2bbf",
              "width": 640
            },
            {
              "height": 300,
              "url": "https://i.scdn.co/image/ab67616d00001e026b3fa88bdd4af566fbbf2bbf",
              "width": 300
            },
            {
              "height": 64,
              "url": "https://i.scdn.co/image/ab67616d000048516b3fa88bdd4af566fbbf2bbf",
              "width": 64
            }
          ],
          "name": "Whatever People Say I Am, That's What I'm Not",
          "release_date": "2006-01-29",
          "release_date_precision": "day",
          "uri": "spotify:album:50Zz8CkIhATKUlQMbHO3k1",
          "artists": [
            {
              "external_urls": {
                "spotify": "https://open.spotify.com/artist/7Ln80lUS6He07XvHI8qqHH"
              },
              "href": "https://api.spotify.com/v1/artists/7Ln80lUS6He07XvHI8qqHH",
              "id": "7Ln80lUS6He07XvHI8qqHH",
              "name": "Arctic Monkeys",
              "type": "artist",
              "uri": "spotify:artist:7Ln80lUS6He07XvHI8qqHH"
            }
          ],
          "external_urls": {
            "spotify": "https://open.spotify.com/album/50Zz8CkIhATKUlQMbHO3k1"
          },
          "total_tracks": 13
        },
        "artists": [
          {
            "external_urls": {
              "spotify": "https://open.spotify.com/artist/7Ln80lUS6He07XvHI8qqHH"
            },
            "href": "https://api.spotify.com/v1/artists/7Ln80lUS6He07XvHI8qqHH",
            "id": "7Ln80lUS6He07XvHI8qqHH",
            "name": "Arctic Monkeys",
            "type": "artist",
            "uri": "spotify:artist:7Ln80lUS6He07XvHI8qqHH"
          }
        ],
        "disc_number": 1,
        "track_number": 11,
        "duration_ms": 202133,
        "external_ids": { "isrc": "GBCEL0501190" },
        "external_urls": {
          "spotify": "https://open.spotify.com/track/2zzLRQ78kKfPTx8FJQCdC2"
        },
        "href": "https://api.spotify.com/v1/tracks/2zzLRQ78kKfPTx8FJQCdC2",
        "id": "2zzLRQ78kKfPTx8FJQCdC2",
        "name": "When The Sun Goes Down",
        "popularity": 74,
        "uri": "spotify:track:2zzLRQ78kKfPTx8FJQCdC2",
        "is_local": false
      },
      "video_thumbnail": { "url": null }
    },
    {
      "added_at": "2022-12-21T03:56:37Z",
      "added_by": {
        "external_urls": {
          "spotify": "https://open.spotify.com/user/urwatilwutsqo"
        },
        "href": "https://api.spotify.com/v1/users/urwatilwutsqo",
        "id": "urwatilwutsqo",
        "type": "user",
        "uri": "spotify:user:urwatilwutsqo"
      },
      "is_local": false,
      "primary_color": null,
      "track": {
        "preview_url": "https://p.scdn.co/mp3-preview/5c501a54dc6591ab71db5c6df8efeafa73de5dde?cid=1a2f7e0ab25046f9bc15e34bc6f6c396",
        "available_markets": [
          "AR",
          "AU",
          "AT",
          "BE",
          "BO",
          "BR",
          "BG",
          "CA",
          "CL",
          "CO",
          "CR",
          "CY",
          "CZ",
          "DK",
          "DO",
          "DE",
          "EC",
          "EE",
          "SV",
          "FI",
          "FR",
          "GR",
          "GT",
          "HN",
          "HK",
          "HU",
          "IS",
          "IE",
          "IT",
          "LV",
          "LT",
          "LU",
          "MY",
          "MT",
          "MX",
          "NL",
          "NZ",
          "NI",
          "NO",
          "PA",
          "PY",
          "PE",
          "PH",
          "PL",
          "PT",
          "SG",
          "SK",
          "ES",
          "SE",
          "CH",
          "TW",
          "TR",
          "UY",
          "US",
          "GB",
          "AD",
          "LI",
          "MC",
          "ID",
          "JP",
          "TH",
          "VN",
          "RO",
          "IL",
          "ZA",
          "SA",
          "AE",
          "BH",
          "QA",
          "OM",
          "KW",
          "EG",
          "MA",
          "DZ",
          "TN",
          "LB",
          "JO",
          "PS",
          "IN",
          "KZ",
          "MD",
          "UA",
          "AL",
          "BA",
          "HR",
          "ME",
          "MK",
          "RS",
          "SI",
          "KR",
          "BD",
          "PK",
          "LK",
          "GH",
          "KE",
          "NG",
          "TZ",
          "UG",
          "AG",
          "AM",
          "BS",
          "BB",
          "BZ",
          "BT",
          "BW",
          "BF",
          "CV",
          "CW",
          "DM",
          "FJ",
          "GM",
          "GE",
          "GD",
          "GW",
          "GY",
          "HT",
          "JM",
          "KI",
          "LS",
          "LR",
          "MW",
          "MV",
          "ML",
          "MH",
          "FM",
          "NA",
          "NR",
          "NE",
          "PW",
          "PG",
          "WS",
          "SM",
          "ST",
          "SN",
          "SC",
          "SL",
          "SB",
          "KN",
          "LC",
          "VC",
          "SR",
          "TL",
          "TO",
          "TT",
          "TV",
          "VU",
          "AZ",
          "BN",
          "BI",
          "KH",
          "CM",
          "TD",
          "KM",
          "GQ",
          "SZ",
          "GA",
          "GN",
          "KG",
          "LA",
          "MO",
          "MR",
          "MN",
          "NP",
          "RW",
          "TG",
          "UZ",
          "ZW",
          "BJ",
          "MG",
          "MU",
          "MZ",
          "AO",
          "CI",
          "DJ",
          "ZM",
          "CD",
          "CG",
          "IQ",
          "LY",
          "TJ",
          "VE",
          "ET",
          "XK"
        ],
        "explicit": false,
        "type": "track",
        "episode": false,
        "track": true,
        "album": {
          "available_markets": [
            "AR",
            "AU",
            "AT",
            "BE",
            "BO",
            "BR",
            "BG",
            "CA",
            "CL",
            "CO",
            "CR",
            "CY",
            "CZ",
            "DK",
            "DO",
            "DE",
            "EC",
            "EE",
            "SV",
            "FI",
            "FR",
            "GR",
            "GT",
            "HN",
            "HK",
            "HU",
            "IS",
            "IE",
            "IT",
            "LV",
            "LT",
            "LU",
            "MY",
            "MT",
            "MX",
            "NL",
            "NZ",
            "NI",
            "NO",
            "PA",
            "PY",
            "PE",
            "PH",
            "PL",
            "PT",
            "SG",
            "SK",
            "ES",
            "SE",
            "CH",
            "TW",
            "TR",
            "UY",
            "US",
            "GB",
            "AD",
            "LI",
            "MC",
            "ID",
            "JP",
            "TH",
            "VN",
            "RO",
            "IL",
            "ZA",
            "SA",
            "AE",
            "BH",
            "QA",
            "OM",
            "KW",
            "EG",
            "MA",
            "DZ",
            "TN",
            "LB",
            "JO",
            "PS",
            "IN",
            "KZ",
            "MD",
            "UA",
            "AL",
            "BA",
            "HR",
            "ME",
            "MK",
            "RS",
            "SI",
            "KR",
            "BD",
            "PK",
            "LK",
            "GH",
            "KE",
            "NG",
            "TZ",
            "UG",
            "AG",
            "AM",
            "BS",
            "BB",
            "BZ",
            "BT",
            "BW",
            "BF",
            "CV",
            "CW",
            "DM",
            "FJ",
            "GM",
            "GE",
            "GD",
            "GW",
            "GY",
            "HT",
            "JM",
            "KI",
            "LS",
            "LR",
            "MW",
            "MV",
            "ML",
            "MH",
            "FM",
            "NA",
            "NR",
            "NE",
            "PW",
            "PG",
            "PR",
            "WS",
            "SM",
            "ST",
            "SN",
            "SC",
            "SL",
            "SB",
            "KN",
            "LC",
            "VC",
            "SR",
            "TL",
            "TO",
            "TT",
            "TV",
            "VU",
            "AZ",
            "BN",
            "BI",
            "KH",
            "CM",
            "TD",
            "KM",
            "GQ",
            "SZ",
            "GA",
            "GN",
            "KG",
            "LA",
            "MO",
            "MR",
            "MN",
            "NP",
            "RW",
            "TG",
            "UZ",
            "ZW",
            "BJ",
            "MG",
            "MU",
            "MZ",
            "AO",
            "CI",
            "DJ",
            "ZM",
            "CD",
            "CG",
            "IQ",
            "LY",
            "TJ",
            "VE",
            "ET",
            "XK"
          ],
          "type": "album",
          "album_type": "album",
          "href": "https://api.spotify.com/v1/albums/50Zz8CkIhATKUlQMbHO3k1",
          "id": "50Zz8CkIhATKUlQMbHO3k1",
          "images": [
            {
              "height": 640,
              "url": "https://i.scdn.co/image/ab67616d0000b2736b3fa88bdd4af566fbbf2bbf",
              "width": 640
            },
            {
              "height": 300,
              "url": "https://i.scdn.co/image/ab67616d00001e026b3fa88bdd4af566fbbf2bbf",
              "width": 300
            },
            {
              "height": 64,
              "url": "https://i.scdn.co/image/ab67616d000048516b3fa88bdd4af566fbbf2bbf",
              "width": 64
            }
          ],
          "name": "Whatever People Say I Am, That's What I'm Not",
          "release_date": "2006-01-29",
          "release_date_precision": "day",
          "uri": "spotify:album:50Zz8CkIhATKUlQMbHO3k1",
          "artists": [
            {
              "external_urls": {
                "spotify": "https://open.spotify.com/artist/7Ln80lUS6He07XvHI8qqHH"
              },
              "href": "https://api.spotify.com/v1/artists/7Ln80lUS6He07XvHI8qqHH",
              "id": "7Ln80lUS6He07XvHI8qqHH",
              "name": "Arctic Monkeys",
              "type": "artist",
              "uri": "spotify:artist:7Ln80lUS6He07XvHI8qqHH"
            }
          ],
          "external_urls": {
            "spotify": "https://open.spotify.com/album/50Zz8CkIhATKUlQMbHO3k1"
          },
          "total_tracks": 13
        },
        "artists": [
          {
            "external_urls": {
              "spotify": "https://open.spotify.com/artist/7Ln80lUS6He07XvHI8qqHH"
            },
            "href": "https://api.spotify.com/v1/artists/7Ln80lUS6He07XvHI8qqHH",
            "id": "7Ln80lUS6He07XvHI8qqHH",
            "name": "Arctic Monkeys",
            "type": "artist",
            "uri": "spotify:artist:7Ln80lUS6He07XvHI8qqHH"
          }
        ],
        "disc_number": 1,
        "track_number": 9,
        "duration_ms": 175440,
        "external_ids": { "isrc": "GBCEL0501188" },
        "external_urls": {
          "spotify": "https://open.spotify.com/track/2fyIS6GXMgUcSv4oejx63f"
        },
        "href": "https://api.spotify.com/v1/tracks/2fyIS6GXMgUcSv4oejx63f",
        "id": "2fyIS6GXMgUcSv4oejx63f",
        "name": "Mardy Bum",
        "popularity": 76,
        "uri": "spotify:track:2fyIS6GXMgUcSv4oejx63f",
        "is_local": false
      },
      "video_thumbnail": { "url": null }
    },
    {
      "added_at": "2022-12-21T03:54:31Z",
      "added_by": {
        "external_urls": {
          "spotify": "https://open.spotify.com/user/urwatilwutsqo"
        },
        "href": "https://api.spotify.com/v1/users/urwatilwutsqo",
        "id": "urwatilwutsqo",
        "type": "user",
        "uri": "spotify:user:urwatilwutsqo"
      },
      "is_local": false,
      "primary_color": null,
      "track": {
        "preview_url": "https://p.scdn.co/mp3-preview/9d8d30ca185e36269b78f26111074c4f10f3f57a?cid=1a2f7e0ab25046f9bc15e34bc6f6c396",
        "available_markets": [],
        "explicit": false,
        "type": "track",
        "episode": false,
        "track": true,
        "album": {
          "available_markets": [],
          "type": "album",
          "album_type": "album",
          "href": "https://api.spotify.com/v1/albums/41vPD50kQ7JeamkxQW7Vuy",
          "id": "41vPD50kQ7JeamkxQW7Vuy",
          "images": [
            {
              "height": 640,
              "url": "https://i.scdn.co/image/ab67616d0000b2730b4f0565f8a790f5105aeb1c",
              "width": 640
            },
            {
              "height": 300,
              "url": "https://i.scdn.co/image/ab67616d00001e020b4f0565f8a790f5105aeb1c",
              "width": 300
            },
            {
              "height": 64,
              "url": "https://i.scdn.co/image/ab67616d000048510b4f0565f8a790f5105aeb1c",
              "width": 64
            }
          ],
          "name": "AM",
          "release_date": "2013-09-10",
          "release_date_precision": "day",
          "uri": "spotify:album:41vPD50kQ7JeamkxQW7Vuy",
          "artists": [
            {
              "external_urls": {
                "spotify": "https://open.spotify.com/artist/7Ln80lUS6He07XvHI8qqHH"
              },
              "href": "https://api.spotify.com/v1/artists/7Ln80lUS6He07XvHI8qqHH",
              "id": "7Ln80lUS6He07XvHI8qqHH",
              "name": "Arctic Monkeys",
              "type": "artist",
              "uri": "spotify:artist:7Ln80lUS6He07XvHI8qqHH"
            }
          ],
          "external_urls": {
            "spotify": "https://open.spotify.com/album/41vPD50kQ7JeamkxQW7Vuy"
          },
          "total_tracks": 12
        },
        "artists": [
          {
            "external_urls": {
              "spotify": "https://open.spotify.com/artist/7Ln80lUS6He07XvHI8qqHH"
            },
            "href": "https://api.spotify.com/v1/artists/7Ln80lUS6He07XvHI8qqHH",
            "id": "7Ln80lUS6He07XvHI8qqHH",
            "name": "Arctic Monkeys",
            "type": "artist",
            "uri": "spotify:artist:7Ln80lUS6He07XvHI8qqHH"
          }
        ],
        "disc_number": 1,
        "track_number": 8,
        "duration_ms": 181026,
        "external_ids": { "isrc": "GBCEL1300369" },
        "external_urls": {
          "spotify": "https://open.spotify.com/track/6MFRtRMQWObCVWE4TC1Pbu"
        },
        "href": "https://api.spotify.com/v1/tracks/6MFRtRMQWObCVWE4TC1Pbu",
        "id": "6MFRtRMQWObCVWE4TC1Pbu",
        "name": "Fireside",
        "popularity": 0,
        "uri": "spotify:track:6MFRtRMQWObCVWE4TC1Pbu",
        "is_local": false
      },
      "video_thumbnail": { "url": null }
    },
    {
      "added_at": "2022-12-21T22:12:09Z",
      "added_by": {
        "external_urls": {
          "spotify": "https://open.spotify.com/user/urwatilwutsqo"
        },
        "href": "https://api.spotify.com/v1/users/urwatilwutsqo",
        "id": "urwatilwutsqo",
        "type": "user",
        "uri": "spotify:user:urwatilwutsqo"
      },
      "is_local": false,
      "primary_color": null,
      "track": {
        "preview_url": "https://p.scdn.co/mp3-preview/c996bfd388171f9a01c59f04b120551eb5fe76b5?cid=1a2f7e0ab25046f9bc15e34bc6f6c396",
        "available_markets": [
          "AR",
          "AU",
          "AT",
          "BE",
          "BO",
          "BR",
          "BG",
          "CA",
          "CL",
          "CO",
          "CR",
          "CY",
          "CZ",
          "DK",
          "DO",
          "DE",
          "EC",
          "EE",
          "SV",
          "FI",
          "FR",
          "GR",
          "GT",
          "HN",
          "HK",
          "HU",
          "IS",
          "IE",
          "IT",
          "LV",
          "LT",
          "LU",
          "MY",
          "MT",
          "MX",
          "NL",
          "NZ",
          "NI",
          "NO",
          "PA",
          "PY",
          "PE",
          "PH",
          "PL",
          "PT",
          "SG",
          "SK",
          "ES",
          "SE",
          "CH",
          "TW",
          "TR",
          "UY",
          "US",
          "GB",
          "AD",
          "LI",
          "MC",
          "ID",
          "JP",
          "TH",
          "VN",
          "RO",
          "IL",
          "ZA",
          "SA",
          "AE",
          "BH",
          "QA",
          "OM",
          "KW",
          "EG",
          "MA",
          "DZ",
          "TN",
          "LB",
          "JO",
          "PS",
          "IN",
          "KZ",
          "MD",
          "UA",
          "AL",
          "BA",
          "HR",
          "ME",
          "MK",
          "RS",
          "SI",
          "KR",
          "BD",
          "PK",
          "LK",
          "GH",
          "KE",
          "NG",
          "TZ",
          "UG",
          "AG",
          "AM",
          "BS",
          "BB",
          "BZ",
          "BT",
          "BW",
          "BF",
          "CV",
          "CW",
          "DM",
          "FJ",
          "GM",
          "GE",
          "GD",
          "GW",
          "GY",
          "HT",
          "JM",
          "KI",
          "LS",
          "LR",
          "MW",
          "MV",
          "ML",
          "MH",
          "FM",
          "NA",
          "NR",
          "NE",
          "PW",
          "PG",
          "WS",
          "SM",
          "ST",
          "SN",
          "SC",
          "SL",
          "SB",
          "KN",
          "LC",
          "VC",
          "SR",
          "TL",
          "TO",
          "TT",
          "TV",
          "VU",
          "AZ",
          "BN",
          "BI",
          "KH",
          "CM",
          "TD",
          "KM",
          "GQ",
          "SZ",
          "GA",
          "GN",
          "KG",
          "LA",
          "MO",
          "MR",
          "MN",
          "NP",
          "RW",
          "TG",
          "UZ",
          "ZW",
          "BJ",
          "MG",
          "MU",
          "MZ",
          "AO",
          "CI",
          "DJ",
          "ZM",
          "CD",
          "CG",
          "IQ",
          "LY",
          "TJ",
          "VE",
          "ET",
          "XK"
        ],
        "explicit": false,
        "type": "track",
        "episode": false,
        "track": true,
        "album": {
          "available_markets": [
            "AR",
            "AU",
            "AT",
            "BE",
            "BO",
            "BR",
            "BG",
            "CA",
            "CL",
            "CO",
            "CR",
            "CY",
            "CZ",
            "DK",
            "DO",
            "DE",
            "EC",
            "EE",
            "SV",
            "FI",
            "FR",
            "GR",
            "GT",
            "HN",
            "HK",
            "HU",
            "IS",
            "IE",
            "IT",
            "LV",
            "LT",
            "LU",
            "MY",
            "MT",
            "MX",
            "NL",
            "NZ",
            "NI",
            "NO",
            "PA",
            "PY",
            "PE",
            "PH",
            "PL",
            "PT",
            "SG",
            "SK",
            "ES",
            "SE",
            "CH",
            "TW",
            "TR",
            "UY",
            "US",
            "GB",
            "AD",
            "LI",
            "MC",
            "ID",
            "JP",
            "TH",
            "VN",
            "RO",
            "IL",
            "ZA",
            "SA",
            "AE",
            "BH",
            "QA",
            "OM",
            "KW",
            "EG",
            "MA",
            "DZ",
            "TN",
            "LB",
            "JO",
            "PS",
            "IN",
            "KZ",
            "MD",
            "UA",
            "AL",
            "BA",
            "HR",
            "ME",
            "MK",
            "RS",
            "SI",
            "KR",
            "BD",
            "PK",
            "LK",
            "GH",
            "KE",
            "NG",
            "TZ",
            "UG",
            "AG",
            "AM",
            "BS",
            "BB",
            "BZ",
            "BT",
            "BW",
            "BF",
            "CV",
            "CW",
            "DM",
            "FJ",
            "GM",
            "GE",
            "GD",
            "GW",
            "GY",
            "HT",
            "JM",
            "KI",
            "LS",
            "LR",
            "MW",
            "MV",
            "ML",
            "MH",
            "FM",
            "NA",
            "NR",
            "NE",
            "PW",
            "PG",
            "PR",
            "WS",
            "SM",
            "ST",
            "SN",
            "SC",
            "SL",
            "SB",
            "KN",
            "LC",
            "VC",
            "SR",
            "TL",
            "TO",
            "TT",
            "TV",
            "VU",
            "AZ",
            "BN",
            "BI",
            "KH",
            "CM",
            "TD",
            "KM",
            "GQ",
            "SZ",
            "GA",
            "GN",
            "KG",
            "LA",
            "MO",
            "MR",
            "MN",
            "NP",
            "RW",
            "TG",
            "UZ",
            "ZW",
            "BJ",
            "MG",
            "MU",
            "MZ",
            "AO",
            "CI",
            "DJ",
            "ZM",
            "CD",
            "CG",
            "IQ",
            "LY",
            "TJ",
            "VE",
            "ET",
            "XK"
          ],
          "type": "album",
          "album_type": "single",
          "href": "https://api.spotify.com/v1/albums/3tEGBDGnejHf4mx1YSqKnb",
          "id": "3tEGBDGnejHf4mx1YSqKnb",
          "images": [
            {
              "height": 640,
              "url": "https://i.scdn.co/image/ab67616d0000b2734fe0b5be5a42d53d5bc645f7",
              "width": 640
            },
            {
              "height": 300,
              "url": "https://i.scdn.co/image/ab67616d00001e024fe0b5be5a42d53d5bc645f7",
              "width": 300
            },
            {
              "height": 64,
              "url": "https://i.scdn.co/image/ab67616d000048514fe0b5be5a42d53d5bc645f7",
              "width": 64
            }
          ],
          "name": "Who The F*** Are Arctic Monkeys?",
          "release_date": "2006-04-22",
          "release_date_precision": "day",
          "uri": "spotify:album:3tEGBDGnejHf4mx1YSqKnb",
          "artists": [
            {
              "external_urls": {
                "spotify": "https://open.spotify.com/artist/7Ln80lUS6He07XvHI8qqHH"
              },
              "href": "https://api.spotify.com/v1/artists/7Ln80lUS6He07XvHI8qqHH",
              "id": "7Ln80lUS6He07XvHI8qqHH",
              "name": "Arctic Monkeys",
              "type": "artist",
              "uri": "spotify:artist:7Ln80lUS6He07XvHI8qqHH"
            }
          ],
          "external_urls": {
            "spotify": "https://open.spotify.com/album/3tEGBDGnejHf4mx1YSqKnb"
          },
          "total_tracks": 5
        },
        "artists": [
          {
            "external_urls": {
              "spotify": "https://open.spotify.com/artist/7Ln80lUS6He07XvHI8qqHH"
            },
            "href": "https://api.spotify.com/v1/artists/7Ln80lUS6He07XvHI8qqHH",
            "id": "7Ln80lUS6He07XvHI8qqHH",
            "name": "Arctic Monkeys",
            "type": "artist",
            "uri": "spotify:artist:7Ln80lUS6He07XvHI8qqHH"
          }
        ],
        "disc_number": 1,
        "track_number": 3,
        "duration_ms": 202853,
        "external_ids": { "isrc": "GBCEL0600171" },
        "external_urls": {
          "spotify": "https://open.spotify.com/track/605E2oDpy3uSIhbRFcrQyn"
        },
        "href": "https://api.spotify.com/v1/tracks/605E2oDpy3uSIhbRFcrQyn",
        "id": "605E2oDpy3uSIhbRFcrQyn",
        "name": "Despair In The Departure Lounge",
        "popularity": 54,
        "uri": "spotify:track:605E2oDpy3uSIhbRFcrQyn",
        "is_local": false
      },
      "video_thumbnail": { "url": null }
    }
  ]
}
