{
  "total": 27,
  "artists": [
    {
      "external_urls": {
        "spotify": "https://open.spotify.com/artist/3mIj9lX2MWuHmhNCA7LSCW"
      },
      "followers": { "href": null, "total": 0 },
      "genres": [
        "modern alternative rock",
        "modern rock",
        "pop",
        "pov: indie",
        "rock"
      ],
      "href": "https://api.spotify.com/v1/artists/3mIj9lX2MWuHmhNCA7LSCW",
      "id": "3mIj9lX2MWuHmhNCA7LSCW",
      "images": [
        {
          "height": 640,
          "url": "https://i.scdn.co/image/ab6761610000e5eb89348336354096fd4e36ca73",
          "width": 640
        },
        {
          "height": 320,
          "url": "https://i.scdn.co/image/ab6761610000517489348336354096fd4e36ca73",
          "width": 320
        },
        {
          "height": 160,
          "url": "https://i.scdn.co/image/ab6761610000f17889348336354096fd4e36ca73",
          "width": 160
        }
      ],
      "name": "The 1975",
      "popularity": 76,
      "type": "artist",
      "uri": "spotify:artist:3mIj9lX2MWuHmhNCA7LSCW"
    },
    {
      "external_urls": {
        "spotify": "https://open.spotify.com/artist/7Ln80lUS6He07XvHI8qqHH"
      },
      "followers": { "href": null, "total": 0 },
      "genres": [
        "garage rock",
        "modern rock",
        "permanent wave",
        "rock",
        "sheffield indie"
      ],
      "href": "https://api.spotify.com/v1/artists/7Ln80lUS6He07XvHI8qqHH",
      "id": "7Ln80lUS6He07XvHI8qqHH",
      "images": [
        {
          "height": 640,
          "url": "https://i.scdn.co/image/ab6761610000e5eb7da39dea0a72f581535fb11f",
          "width": 640
        },
        {
          "height": 320,
          "url": "https://i.scdn.co/image/ab676161000051747da39dea0a72f581535fb11f",
          "width": 320
        },
        {
          "height": 160,
          "url": "https://i.scdn.co/image/ab6761610000f1787da39dea0a72f581535fb11f",
          "width": 160
        }
      ],
      "name": "Arctic Monkeys",
      "popularity": 86,
      "type": "artist",
      "uri": "spotify:artist:7Ln80lUS6He07XvHI8qqHH"
    },
    {
      "external_urls": {
        "spotify": "https://open.spotify.com/artist/2kxP07DLgs4xlWz8YHlvfh"
      },
      "followers": { "href": null, "total": 0 },
      "genres": ["indonesian r&b"],
      "href": "https://api.spotify.com/v1/artists/2kxP07DLgs4xlWz8YHlvfh",
      "id": "2kxP07DLgs4xlWz8YHlvfh",
      "images": [
        {
          "height": 640,
          "url": "https://i.scdn.co/image/ab6761610000e5ebad807774e95b4e8febb1a79a",
          "width": 640
        },
        {
          "height": 320,
          "url": "https://i.scdn.co/image/ab67616100005174ad807774e95b4e8febb1a79a",
          "width": 320
        },
        {
          "height": 160,
          "url": "https://i.scdn.co/image/ab6761610000f178ad807774e95b4e8febb1a79a",
          "width": 160
        }
      ],
      "name": "NIKI",
      "popularity": 76,
      "type": "artist",
      "uri": "spotify:artist:2kxP07DLgs4xlWz8YHlvfh"
    },
    {
      "external_urls": {
        "spotify": "https://open.spotify.com/artist/7pbDxGE6nQSZVfiFdq9lOL"
      },
      "followers": { "href": null, "total": 0 },
      "genres": ["bedroom pop"],
      "href": "https://api.spotify.com/v1/artists/7pbDxGE6nQSZVfiFdq9lOL",
      "id": "7pbDxGE6nQSZVfiFdq9lOL",
      "images": [
        {
          "height": 640,
          "url": "https://i.scdn.co/image/ab6761610000e5ebffb90f91cb2f487d7309f7bc",
          "width": 640
        },
        {
          "height": 320,
          "url": "https://i.scdn.co/image/ab67616100005174ffb90f91cb2f487d7309f7bc",
          "width": 320
        },
        {
          "height": 160,
          "url": "https://i.scdn.co/image/ab6761610000f178ffb90f91cb2f487d7309f7bc",
          "width": 160
        }
      ],
      "name": "Rex Orange County",
      "popularity": 73,
      "type": "artist",
      "uri": "spotify:artist:7pbDxGE6nQSZVfiFdq9lOL"
    },
    {
      "external_urls": {
        "spotify": "https://open.spotify.com/artist/06HL4z0CvFAxyc27GXpf02"
      },
      "followers": { "href": null, "total": 0 },
      "genres": ["pop"],
      "href": "https://api.spotify.com/v1/artists/06HL4z0CvFAxyc27GXpf02",
      "id": "06HL4z0CvFAxyc27GXpf02",
      "images": [
        {
          "height": 640,
          "url": "https://i.scdn.co/image/ab6761610000e5eb859e4c14fa59296c8649e0e4",
          "width": 640
        },
        {
          "height": 320,
          "url": "https://i.scdn.co/image/ab67616100005174859e4c14fa59296c8649e0e4",
          "width": 320
        },
        {
          "height": 160,
          "url": "https://i.scdn.co/image/ab6761610000f178859e4c14fa59296c8649e0e4",
          "width": 160
        }
      ],
      "name": "Taylor Swift",
      "popularity": 100,
      "type": "artist",
      "uri": "spotify:artist:06HL4z0CvFAxyc27GXpf02"
    },
    {
      "external_urls": {
        "spotify": "https://open.spotify.com/artist/77SW9BnxLY8rJ0RciFqkHh"
      },
      "followers": { "href": null, "total": 0 },
      "genres": ["modern alternative rock", "modern rock", "pop"],
      "href": "https://api.spotify.com/v1/artists/77SW9BnxLY8rJ0RciFqkHh",
      "id": "77SW9BnxLY8rJ0RciFqkHh",
      "images": [
        {
          "height": 640,
          "url": "https://i.scdn.co/image/ab6761610000e5ebdf0b5ac84376a0a4b2166816",
          "width": 640
        },
        {
          "height": 320,
          "url": "https://i.scdn.co/image/ab67616100005174df0b5ac84376a0a4b2166816",
          "width": 320
        },
        {
          "height": 160,
          "url": "https://i.scdn.co/image/ab6761610000f178df0b5ac84376a0a4b2166816",
          "width": 160
        }
      ],
      "name": "The Neighbourhood",
      "popularity": 83,
      "type": "artist",
      "uri": "spotify:artist:77SW9BnxLY8rJ0RciFqkHh"
    },
    {
      "external_urls": {
        "spotify": "https://open.spotify.com/artist/0epOFNiUfyON9EYx7Tpr6V"
      },
      "followers": { "href": null, "total": 0 },
      "genres": [
        "alternative rock",
        "garage rock",
        "modern rock",
        "permanent wave",
        "rock"
      ],
      "href": "https://api.spotify.com/v1/artists/0epOFNiUfyON9EYx7Tpr6V",
      "id": "0epOFNiUfyON9EYx7Tpr6V",
      "images": [
        {
          "height": 640,
          "url": "https://i.scdn.co/image/ab6761610000e5ebc3b137793230f4043feb0089",
          "width": 640
        },
        {
          "height": 320,
          "url": "https://i.scdn.co/image/ab67616100005174c3b137793230f4043feb0089",
          "width": 320
        },
        {
          "height": 160,
          "url": "https://i.scdn.co/image/ab6761610000f178c3b137793230f4043feb0089",
          "width": 160
        }
      ],
      "name": "The Strokes",
      "popularity": 75,
      "type": "artist",
      "uri": "spotify:artist:0epOFNiUfyON9EYx7Tpr6V"
    },
    {
      "external_urls": {
        "spotify": "https://open.spotify.com/artist/31aMmlq8isIAgojvmIwiS4"
      },
      "followers": { "href": null, "total": 0 },
      "genres": ["indonesian alternative rock", "indonesian pop"],
      "href": "https://api.spotify.com/v1/artists/31aMmlq8isIAgojvmIwiS4",
      "id": "31aMmlq8isIAgojvmIwiS4",
      "images": [
        {
          "height": 640,
          "url": "https://i.scdn.co/image/ab6761610000e5eb993a01b962e04058bcf5c28a",
          "width": 640
        },
        {
          "height": 320,
          "url": "https://i.scdn.co/image/ab67616100005174993a01b962e04058bcf5c28a",
          "width": 320
        },
        {
          "height": 160,
          "url": "https://i.scdn.co/image/ab6761610000f178993a01b962e04058bcf5c28a",
          "width": 160
        }
      ],
      "name": "Noah",
      "popularity": 66,
      "type": "artist",
      "uri": "spotify:artist:31aMmlq8isIAgojvmIwiS4"
    },
    {
      "external_urls": {
        "spotify": "https://open.spotify.com/artist/51kyrUsAVqUBcoDEMFkX12"
      },
      "followers": { "href": null, "total": 0 },
      "genres": ["indonesian pop"],
      "href": "https://api.spotify.com/v1/artists/51kyrUsAVqUBcoDEMFkX12",
      "id": "51kyrUsAVqUBcoDEMFkX12",
      "images": [
        {
          "height": 640,
          "url": "https://i.scdn.co/image/ab6761610000e5eb324cea967a456ee680bf6b92",
          "width": 640
        },
        {
          "height": 320,
          "url": "https://i.scdn.co/image/ab67616100005174324cea967a456ee680bf6b92",
          "width": 320
        },
        {
          "height": 160,
          "url": "https://i.scdn.co/image/ab6761610000f178324cea967a456ee680bf6b92",
          "width": 160
        }
      ],
      "name": "Hindia",
      "popularity": 71,
      "type": "artist",
      "uri": "spotify:artist:51kyrUsAVqUBcoDEMFkX12"
    },
    {
      "external_urls": {
        "spotify": "https://open.spotify.com/artist/6KImCVD70vtIoJWnq6nGn3"
      },
      "followers": { "href": null, "total": 0 },
      "genres": ["pop"],
      "href": "https://api.spotify.com/v1/artists/6KImCVD70vtIoJWnq6nGn3",
      "id": "6KImCVD70vtIoJWnq6nGn3",
      "images": [
        {
          "height": 640,
          "url": "https://i.scdn.co/image/ab6761610000e5ebf7db7c8ede90a019c54590bb",
          "width": 640
        },
        {
          "height": 320,
          "url": "https://i.scdn.co/image/ab67616100005174f7db7c8ede90a019c54590bb",
          "width": 320
        },
        {
          "height": 160,
          "url": "https://i.scdn.co/image/ab6761610000f178f7db7c8ede90a019c54590bb",
          "width": 160
        }
      ],
      "name": "Harry Styles",
      "popularity": 85,
      "type": "artist",
      "uri": "spotify:artist:6KImCVD70vtIoJWnq6nGn3"
    },
    {
      "external_urls": {
        "spotify": "https://open.spotify.com/artist/4IWBUUAFIplrNtaOHcJPRM"
      },
      "followers": { "href": null, "total": 0 },
      "genres": ["pop", "talent show", "uk pop"],
      "href": "https://api.spotify.com/v1/artists/4IWBUUAFIplrNtaOHcJPRM",
      "id": "4IWBUUAFIplrNtaOHcJPRM",
      "images": [
        {
          "height": 640,
          "url": "https://i.scdn.co/image/ab6761610000e5eb2a0c6d0343c82be9dd6fce0b",
          "width": 640
        },
        {
          "height": 320,
          "url": "https://i.scdn.co/image/ab676161000051742a0c6d0343c82be9dd6fce0b",
          "width": 320
        },
        {
          "height": 160,
          "url": "https://i.scdn.co/image/ab6761610000f1782a0c6d0343c82be9dd6fce0b",
          "width": 160
        }
      ],
      "name": "James Arthur",
      "popularity": 82,
      "type": "artist",
      "uri": "spotify:artist:4IWBUUAFIplrNtaOHcJPRM"
    },
    {
      "external_urls": {
        "spotify": "https://open.spotify.com/artist/1Xyo4u8uXC1ZmMpatF05PJ"
      },
      "followers": { "href": null, "total": 0 },
      "genres": ["canadian contemporary r&b", "canadian pop", "pop"],
      "href": "https://api.spotify.com/v1/artists/1Xyo4u8uXC1ZmMpatF05PJ",
      "id": "1Xyo4u8uXC1ZmMpatF05PJ",
      "images": [
        {
          "height": 640,
          "url": "https://i.scdn.co/image/ab6761610000e5eb214f3cf1cbe7139c1e26ffbb",
          "width": 640
        },
        {
          "height": 320,
          "url": "https://i.scdn.co/image/ab67616100005174214f3cf1cbe7139c1e26ffbb",
          "width": 320
        },
        {
          "height": 160,
          "url": "https://i.scdn.co/image/ab6761610000f178214f3cf1cbe7139c1e26ffbb",
          "width": 160
        }
      ],
      "name": "The Weeknd",
      "popularity": 95,
      "type": "artist",
      "uri": "spotify:artist:1Xyo4u8uXC1ZmMpatF05PJ"
    },
    {
      "external_urls": {
        "spotify": "https://open.spotify.com/artist/3uwAm6vQy7kWPS2bciKWx9"
      },
      "followers": { "href": null, "total": 0 },
      "genres": ["bedroom pop", "indie pop", "norwegian indie", "pov: indie"],
      "href": "https://api.spotify.com/v1/artists/3uwAm6vQy7kWPS2bciKWx9",
      "id": "3uwAm6vQy7kWPS2bciKWx9",
      "images": [
        {
          "height": 640,
          "url": "https://i.scdn.co/image/ab6761610000e5ebb24bd3a4e9f9a6a169e0f4f4",
          "width": 640
        },
        {
          "height": 320,
          "url": "https://i.scdn.co/image/ab67616100005174b24bd3a4e9f9a6a169e0f4f4",
          "width": 320
        },
        {
          "height": 160,
          "url": "https://i.scdn.co/image/ab6761610000f178b24bd3a4e9f9a6a169e0f4f4",
          "width": 160
        }
      ],
      "name": "girl in red",
      "popularity": 74,
      "type": "artist",
      "uri": "spotify:artist:3uwAm6vQy7kWPS2bciKWx9"
    },
    {
      "external_urls": {
        "spotify": "https://open.spotify.com/artist/4AK6F7OLvEQ5QYCBNiQWHq"
      },
      "followers": { "href": null, "total": 0 },
      "genres": ["boy band", "pop", "post-teen pop", "talent show"],
      "href": "https://api.spotify.com/v1/artists/4AK6F7OLvEQ5QYCBNiQWHq",
      "id": "4AK6F7OLvEQ5QYCBNiQWHq",
      "images": [
        {
          "height": 1000,
          "url": "https://i.scdn.co/image/5bb443424a1ad71603c43d67f5af1a04da6bb3c8",
          "width": 1000
        },
        {
          "height": 640,
          "url": "https://i.scdn.co/image/289c7f686f5b78ceeb224453cf9a15697a678a79",
          "width": 640
        },
        {
          "height": 200,
          "url": "https://i.scdn.co/image/45741ba38b51130bb96e00c0e24d17ba311a9293",
          "width": 200
        },
        {
          "height": 64,
          "url": "https://i.scdn.co/image/6c89c662ad0ab75bc2af9a3ae2b16f811daced50",
          "width": 64
        }
      ],
      "name": "One Direction",
      "popularity": 83,
      "type": "artist",
      "uri": "spotify:artist:4AK6F7OLvEQ5QYCBNiQWHq"
    },
    {
      "external_urls": {
        "spotify": "https://open.spotify.com/artist/4gzpq5DPGxSnKTe4SA8HAU"
      },
      "followers": { "href": null, "total": 0 },
      "genres": ["permanent wave", "pop"],
      "href": "https://api.spotify.com/v1/artists/4gzpq5DPGxSnKTe4SA8HAU",
      "id": "4gzpq5DPGxSnKTe4SA8HAU",
      "images": [
        {
          "height": 640,
          "url": "https://i.scdn.co/image/ab6761610000e5eb989ed05e1f0570cc4726c2d3",
          "width": 640
        },
        {
          "height": 320,
          "url": "https://i.scdn.co/image/ab67616100005174989ed05e1f0570cc4726c2d3",
          "width": 320
        },
        {
          "height": 160,
          "url": "https://i.scdn.co/image/ab6761610000f178989ed05e1f0570cc4726c2d3",
          "width": 160
        }
      ],
      "name": "Coldplay",
      "popularity": 88,
      "type": "artist",
      "uri": "spotify:artist:4gzpq5DPGxSnKTe4SA8HAU"
    },
    {
      "external_urls": {
        "spotify": "https://open.spotify.com/artist/6HvZYsbFfjnjFrWF950C9d"
      },
      "followers": { "href": null, "total": 0 },
      "genres": ["k-pop", "k-pop girl group"],
      "href": "https://api.spotify.com/v1/artists/6HvZYsbFfjnjFrWF950C9d",
      "id": "6HvZYsbFfjnjFrWF950C9d",
      "images": [
        {
          "height": 640,
          "url": "https://i.scdn.co/image/ab6761610000e5ebf5d2200231e6ad75e8485476",
          "width": 640
        },
        {
          "height": 320,
          "url": "https://i.scdn.co/image/ab67616100005174f5d2200231e6ad75e8485476",
          "width": 320
        },
        {
          "height": 160,
          "url": "https://i.scdn.co/image/ab6761610000f178f5d2200231e6ad75e8485476",
          "width": 160
        }
      ],
      "name": "NewJeans",
      "popularity": 82,
      "type": "artist",
      "uri": "spotify:artist:6HvZYsbFfjnjFrWF950C9d"
    },
    {
      "external_urls": {
        "spotify": "https://open.spotify.com/artist/4dpARuHxo51G3z768sgnrY"
      },
      "followers": { "href": null, "total": 0 },
      "genres": ["british soul", "pop", "pop soul", "uk pop"],
      "href": "https://api.spotify.com/v1/artists/4dpARuHxo51G3z768sgnrY",
      "id": "4dpARuHxo51G3z768sgnrY",
      "images": [
        {
          "height": 640,
          "url": "https://i.scdn.co/image/ab6761610000e5eb68f6e5892075d7f22615bd17",
          "width": 640
        },
        {
          "height": 320,
          "url": "https://i.scdn.co/image/ab6761610000517468f6e5892075d7f22615bd17",
          "width": 320
        },
        {
          "height": 160,
          "url": "https://i.scdn.co/image/ab6761610000f17868f6e5892075d7f22615bd17",
          "width": 160
        }
      ],
      "name": "Adele",
      "popularity": 85,
      "type": "artist",
      "uri": "spotify:artist:4dpARuHxo51G3z768sgnrY"
    },
    {
      "external_urls": {
        "spotify": "https://open.spotify.com/artist/74XFHRwlV6OrjEM0A2NCMF"
      },
      "followers": { "href": null, "total": 0 },
      "genres": [
        "candy pop",
        "modern rock",
        "pixie",
        "pop",
        "pop emo",
        "pop punk",
        "rock"
      ],
      "href": "https://api.spotify.com/v1/artists/74XFHRwlV6OrjEM0A2NCMF",
      "id": "74XFHRwlV6OrjEM0A2NCMF",
      "images": [
        {
          "height": 640,
          "url": "https://i.scdn.co/image/ab6761610000e5ebb10c34546a4ca2d7faeb8865",
          "width": 640
        },
        {
          "height": 320,
          "url": "https://i.scdn.co/image/ab67616100005174b10c34546a4ca2d7faeb8865",
          "width": 320
        },
        {
          "height": 160,
          "url": "https://i.scdn.co/image/ab6761610000f178b10c34546a4ca2d7faeb8865",
          "width": 160
        }
      ],
      "name": "Paramore",
      "popularity": 77,
      "type": "artist",
      "uri": "spotify:artist:74XFHRwlV6OrjEM0A2NCMF"
    },
    {
      "external_urls": {
        "spotify": "https://open.spotify.com/artist/0Y6dVaC9DZtPNH4591M42W"
      },
      "followers": { "href": null, "total": 0 },
      "genres": ["pov: indie"],
      "href": "https://api.spotify.com/v1/artists/0Y6dVaC9DZtPNH4591M42W",
      "id": "0Y6dVaC9DZtPNH4591M42W",
      "images": [
        {
          "height": 640,
          "url": "https://i.scdn.co/image/ab67616d0000b27332f5fec7a879ed6ef28f0dfd",
          "width": 640
        },
        {
          "height": 300,
          "url": "https://i.scdn.co/image/ab67616d00001e0232f5fec7a879ed6ef28f0dfd",
          "width": 300
        },
        {
          "height": 64,
          "url": "https://i.scdn.co/image/ab67616d0000485132f5fec7a879ed6ef28f0dfd",
          "width": 64
        }
      ],
      "name": "TV Girl",
      "popularity": 82,
      "type": "artist",
      "uri": "spotify:artist:0Y6dVaC9DZtPNH4591M42W"
    },
    {
      "external_urls": {
        "spotify": "https://open.spotify.com/artist/1WgXqy2Dd70QQOU7Ay074N"
      },
      "followers": { "href": null, "total": 0 },
      "genres": ["art pop", "norwegian pop"],
      "href": "https://api.spotify.com/v1/artists/1WgXqy2Dd70QQOU7Ay074N",
      "id": "1WgXqy2Dd70QQOU7Ay074N",
      "images": [
        {
          "height": 640,
          "url": "https://i.scdn.co/image/ab6761610000e5eb68369596eaf232b28b63d583",
          "width": 640
        },
        {
          "height": 320,
          "url": "https://i.scdn.co/image/ab6761610000517468369596eaf232b28b63d583",
          "width": 320
        },
        {
          "height": 160,
          "url": "https://i.scdn.co/image/ab6761610000f17868369596eaf232b28b63d583",
          "width": 160
        }
      ],
      "name": "AURORA",
      "popularity": 72,
      "type": "artist",
      "uri": "spotify:artist:1WgXqy2Dd70QQOU7Ay074N"
    },
    {
      "external_urls": {
        "spotify": "https://open.spotify.com/artist/2uYWxilOVlUdk4oV9DvwqK"
      },
      "followers": { "href": null, "total": 0 },
      "genres": ["brooklyn indie", "pov: indie"],
      "href": "https://api.spotify.com/v1/artists/2uYWxilOVlUdk4oV9DvwqK",
      "id": "2uYWxilOVlUdk4oV9DvwqK",
      "images": [
        {
          "height": 640,
          "url": "https://i.scdn.co/image/ab6761610000e5eb4bdb3888818637acb71c4a13",
          "width": 640
        },
        {
          "height": 320,
          "url": "https://i.scdn.co/image/ab676161000051744bdb3888818637acb71c4a13",
          "width": 320
        },
        {
          "height": 160,
          "url": "https://i.scdn.co/image/ab6761610000f1784bdb3888818637acb71c4a13",
          "width": 160
        }
      ],
      "name": "Mitski",
      "popularity": 84,
      "type": "artist",
      "uri": "spotify:artist:2uYWxilOVlUdk4oV9DvwqK"
    },
    {
      "external_urls": {
        "spotify": "https://open.spotify.com/artist/3yY2gUcIsjMr8hjo51PoJ8"
      },
      "followers": { "href": null, "total": 0 },
      "genres": [
        "madchester",
        "new wave",
        "permanent wave",
        "rock",
        "uk post-punk"
      ],
      "href": "https://api.spotify.com/v1/artists/3yY2gUcIsjMr8hjo51PoJ8",
      "id": "3yY2gUcIsjMr8hjo51PoJ8",
      "images": [
        {
          "height": 1516,
          "url": "https://i.scdn.co/image/481b980af463122013e4578c08fb8c5cbfaed1e9",
          "width": 1000
        },
        {
          "height": 970,
          "url": "https://i.scdn.co/image/4bf08a9e6eea088b20d4092d1322bbd3f39ff9af",
          "width": 640
        },
        {
          "height": 303,
          "url": "https://i.scdn.co/image/bd4c7f5ff2c5c4385604e60c71eac1dd498ddbd9",
          "width": 200
        },
        {
          "height": 97,
          "url": "https://i.scdn.co/image/d3a2542f2811b5b01ee3483ec7c193f72a882ea1",
          "width": 64
        }
      ],
      "name": "The Smiths",
      "popularity": 78,
      "type": "artist",
      "uri": "spotify:artist:3yY2gUcIsjMr8hjo51PoJ8"
    },
    {
      "external_urls": {
        "spotify": "https://open.spotify.com/artist/46U5WmejGzsPqUiw3Uw0Xq"
      },
      "followers": { "href": null, "total": 0 },
      "genres": [],
      "href": "https://api.spotify.com/v1/artists/46U5WmejGzsPqUiw3Uw0Xq",
      "id": "46U5WmejGzsPqUiw3Uw0Xq",
      "images": [
        {
          "height": 640,
          "url": "https://i.scdn.co/image/ab6761610000e5eb0b4aa87b211493c492eb03e5",
          "width": 640
        },
        {
          "height": 320,
          "url": "https://i.scdn.co/image/ab676161000051740b4aa87b211493c492eb03e5",
          "width": 320
        },
        {
          "height": 160,
          "url": "https://i.scdn.co/image/ab6761610000f1780b4aa87b211493c492eb03e5",
          "width": 160
        }
      ],
      "name": "Vian Izak",
      "popularity": 47,
      "type": "artist",
      "uri": "spotify:artist:46U5WmejGzsPqUiw3Uw0Xq"
    },
    {
      "external_urls": {
        "spotify": "https://open.spotify.com/artist/4V8LLVI7PbaPR0K2TGSxFF"
      },
      "followers": { "href": null, "total": 0 },
      "genres": ["hip hop", "rap"],
      "href": "https://api.spotify.com/v1/artists/4V8LLVI7PbaPR0K2TGSxFF",
      "id": "4V8LLVI7PbaPR0K2TGSxFF",
      "images": [
        {
          "height": 640,
          "url": "https://i.scdn.co/image/ab6761610000e5eb8278b782cbb5a3963db88ada",
          "width": 640
        },
        {
          "height": 320,
          "url": "https://i.scdn.co/image/ab676161000051748278b782cbb5a3963db88ada",
          "width": 320
        },
        {
          "height": 160,
          "url": "https://i.scdn.co/image/ab6761610000f1788278b782cbb5a3963db88ada",
          "width": 160
        }
      ],
      "name": "Tyler, The Creator",
      "popularity": 84,
      "type": "artist",
      "uri": "spotify:artist:4V8LLVI7PbaPR0K2TGSxFF"
    },
    {
      "external_urls": {
        "spotify": "https://open.spotify.com/artist/4phGZZrJZRo4ElhRtViYdl"
      },
      "followers": { "href": null, "total": 0 },
      "genres": ["acoustic pop", "dance pop", "neo mellow", "pop"],
      "href": "https://api.spotify.com/v1/artists/4phGZZrJZRo4ElhRtViYdl",
      "id": "4phGZZrJZRo4ElhRtViYdl",
      "images": [
        {
          "height": 640,
          "url": "https://i.scdn.co/image/ab6761610000e5ebc3b370fc26c83312db52af14",
          "width": 640
        },
        {
          "height": 320,
          "url": "https://i.scdn.co/image/ab67616100005174c3b370fc26c83312db52af14",
          "width": 320
        },
        {
          "height": 160,
          "url": "https://i.scdn.co/image/ab6761610000f178c3b370fc26c83312db52af14",
          "width": 160
        }
      ],
      "name": "Jason Mraz",
      "popularity": 72,
      "type": "artist",
      "uri": "spotify:artist:4phGZZrJZRo4ElhRtViYdl"
    },
    {
      "external_urls": {
        "spotify": "https://open.spotify.com/artist/5INjqkS1o8h1imAzPqGZBb"
      },
      "followers": { "href": null, "total": 0 },
      "genres": ["australian psych", "modern rock", "neo-psychedelic", "rock"],
      "href": "https://api.spotify.com/v1/artists/5INjqkS1o8h1imAzPqGZBb",
      "id": "5INjqkS1o8h1imAzPqGZBb",
      "images": [
        {
          "height": 640,
          "url": "https://i.scdn.co/image/ab6761610000e5eb90357ef28b3a012a1d1b2fa2",
          "width": 640
        },
        {
          "height": 320,
          "url": "https://i.scdn.co/image/ab6761610000517490357ef28b3a012a1d1b2fa2",
          "width": 320
        },
        {
          "height": 160,
          "url": "https://i.scdn.co/image/ab6761610000f17890357ef28b3a012a1d1b2fa2",
          "width": 160
        }
      ],
      "name": "Tame Impala",
      "popularity": 80,
      "type": "artist",
      "uri": "spotify:artist:5INjqkS1o8h1imAzPqGZBb"
    },
    {
      "external_urls": {
        "spotify": "https://open.spotify.com/artist/7t0rwkOPGlDPEhaOcVtOt9"
      },
      "followers": { "href": null, "total": 0 },
      "genres": ["irish rock", "pop rock", "rock"],
      "href": "https://api.spotify.com/v1/artists/7t0rwkOPGlDPEhaOcVtOt9",
      "id": "7t0rwkOPGlDPEhaOcVtOt9",
      "images": [
        {
          "height": 667,
          "url": "https://i.scdn.co/image/143c01f407ed64a4b3bcbc92d24c05ef80981251",
          "width": 1000
        },
        {
          "height": 427,
          "url": "https://i.scdn.co/image/a82245ec62ee9606ab456d787f1f7fcd788e6a10",
          "width": 640
        },
        {
          "height": 133,
          "url": "https://i.scdn.co/image/3a0e3d6f957d3d713a386aeedd028a8e8a1d8803",
          "width": 200
        },
        {
          "height": 43,
          "url": "https://i.scdn.co/image/95b4d133c1e6a19efb05e4becf0f9c46e0894845",
          "width": 64
        }
      ],
      "name": "The Cranberries",
      "popularity": 74,
      "type": "artist",
      "uri": "spotify:artist:7t0rwkOPGlDPEhaOcVtOt9"
    }
  ]
}
